{
  "8b860863-df14-4e33-a8ff-82db20e7a44e": [
    {
      "questionId": "eb011229-b553-4b29-9037-8459eea5c194",
      "answer": false
    },
    {
      "questionId": "d92e06ba-5f03-4188-93be-13ed049a91d7",
      "answer": false
    },
    {
      "questionId": "d2e39e39-19bf-4840-8e01-61791fb58ba6",
      "answer": false,
      "comment": "Tvrzení by měla být založena na pravdě. Mnoho vědeckých studií v posledních desítkách let byla úplně mimo realitu."
    },
    {
      "questionId": "802ca7b6-2b85-4056-8f24-a062c6b7aa3e",
      "answer": false
    },
    {
      "questionId": "2b8e4a89-b082-4566-870b-df79faa09f3a",
      "answer": false,
      "comment": "O sociální služby by se měl stát postarat sám."
    },
    {
      "questionId": "72c1cf07-c617-467a-84d1-7e4e1560221e",
      "answer": true,
      "comment": "Pokud majitel neprokáže nájemní smlouvou, že ho dlouhodobě nepronajímá někomu jinému za účelem bydlení."
    },
    {
      "questionId": "02bccd7b-7c7d-4533-9744-161c32d9acc7",
      "answer": false,
      "comment": "Jsme zastupitelská demokracie."
    },
    {
      "questionId": "601aacd3-d095-4801-a5fa-9ecc5866897d",
      "answer": true,
      "comment": "Jsem pro úplné zrušení systému exekutorů."
    },
    {
      "questionId": "c20fa265-0cc9-4bd1-82c8-90f199c68822",
      "answer": false
    },
    {
      "questionId": "5246fb1f-d2ff-4208-986b-c75eef1726ef",
      "answer": true
    },
    {
      "questionId": "dfa34db8-1fce-4e03-bc74-023c851635dc",
      "answer": true
    },
    {
      "questionId": "a44b2eda-e3e9-46c0-84d3-b54384f69c4e",
      "answer": true
    },
    {
      "questionId": "b52cb4c1-ec9d-40bc-9801-3d664a491d56",
      "answer": false
    },
    {
      "questionId": "5639fb63-b567-4961-8ce4-145eb286f3d3",
      "answer": true
    },
    {
      "questionId": "db9c7221-9a8d-44bb-af2b-47c8f6b03d56",
      "answer": false
    },
    {
      "questionId": "36847062-6427-40d0-80fb-f0f57934dc90",
      "answer": true
    },
    {
      "questionId": "931cf702-396e-4a2b-a0c7-db2a2d051f05",
      "answer": false,
      "comment": "Naopak sociální sítě nesmějí sami cenzurovat a omezovat obsah uživatelů."
    },
    {
      "questionId": "2deb4e7d-fc56-48b2-99c9-43ac0eb17809",
      "answer": false,
      "comment": "Kdo rozhodne co je informace a co dezinformace? Pokud budou mít lidé k dispozici pouze jednu verzi náhledu na věc, tak se nebudou nikdy schopni správně rozhodnout."
    },
    {
      "questionId": "7d1d35e0-12b5-46af-ac08-1c3c64862103",
      "answer": null,
      "comment": "To si musí rozhodnout Ukrajina. Rozhodně jsem proti podpoře válečného úsilí Ukrajiny."
    },
    {
      "questionId": "9cf8aae5-681b-4fe7-b215-f0818f89b68e",
      "answer": false
    },
    {
      "questionId": "07b8e1f9-79e1-4f17-af33-b9114e0bd75e",
      "answer": false,
      "comment": "Je třeba vidět všechny aspekty speciální operace Ruska na Ukrajině, co tomu předcházelo a co k tomu Rusko donutilo."
    },
    {
      "questionId": "4bb73b72-2610-46e2-a891-f093858ae0ad",
      "answer": false
    },
    {
      "questionId": "78d3f289-6d60-4af0-b2e9-06154ff4124c",
      "answer": true
    },
    {
      "questionId": "5f2bebd3-ed6b-44f6-971b-ceafeafd6cd4",
      "answer": false
    },
    {
      "questionId": "c0a9c9c6-c36b-4c83-b02d-3f704f697d6c",
      "answer": false
    },
    {
      "questionId": "a94a2af4-3b3e-4a43-a936-4b393ddbcdb7",
      "answer": true
    },
    {
      "questionId": "b31ccd80-369f-4224-8e86-8aa44664b80b",
      "answer": false
    },
    {
      "questionId": "226b8e98-32b3-42f5-b4e4-6ab2b2b06c87",
      "answer": true
    },
    {
      "questionId": "7b3ac5c9-b2a2-45cc-928d-c876949a2b7f",
      "answer": false
    },
    {
      "questionId": "e3c15681-0a1c-4e62-bc2f-2d89088856a9",
      "answer": true
    },
    {
      "questionId": "088029ea-c9fe-4abb-bdc7-4c1faa2c007f",
      "answer": true
    },
    {
      "questionId": "dc4b3ed9-80d5-4c0f-976b-9dd0f44b5df6",
      "answer": true
    },
    {
      "questionId": "fc8daca8-7035-415c-9ab5-5cff0ec01e2c",
      "answer": true
    },
    {
      "questionId": "db7b8164-71d8-4f4b-8d78-4abebcc17847",
      "answer": false
    },
    {
      "questionId": "dbf45b5e-1e11-45e2-a037-18d9bf18353f",
      "answer": false
    }
  ],
  "c7665a87-7d3d-4fc6-9864-619ff956a776": [
    {
      "questionId": "eb011229-b553-4b29-9037-8459eea5c194",
      "answer": true,
      "comment": "Ano, i když některá ustavení českou realitu. Chápu ale, že v evropských zemích se silnými pristěhoveleckými komunitami, můžou mít svůj význam, pokud jde o násilí na ženách."
    },
    {
      "questionId": "d92e06ba-5f03-4188-93be-13ed049a91d7",
      "answer": true
    },
    {
      "questionId": "d2e39e39-19bf-4840-8e01-61791fb58ba6",
      "answer": null
    },
    {
      "questionId": "802ca7b6-2b85-4056-8f24-a062c6b7aa3e",
      "answer": true
    },
    {
      "questionId": "2b8e4a89-b082-4566-870b-df79faa09f3a",
      "answer": true
    },
    {
      "questionId": "72c1cf07-c617-467a-84d1-7e4e1560221e",
      "answer": false,
      "comment": "Protože se to posléze promítne do výše nájmu a zaplatí to nájemník. Moje komunální zkušenost mi říká, že mnohem větší pomocí v bytové výstavbě by bylo rychlé územní a stavební řízení. Není přece možné, aby to trvalo měsíce a měsíce… Podobně je to se změnami územních plánů. Pokud se povede prosadit tzv. Zkrácené řízení, je to i tak minimálně na 18 měsíců. Pokud jde o byty měla by existovat snazší schvalovací procedura."
    },
    {
      "questionId": "02bccd7b-7c7d-4533-9744-161c32d9acc7",
      "answer": false
    },
    {
      "questionId": "601aacd3-d095-4801-a5fa-9ecc5866897d",
      "answer": false,
      "comment": "Velká novela exekučního řádu v tomto ohledu mnohé rozumně upravila."
    },
    {
      "questionId": "c20fa265-0cc9-4bd1-82c8-90f199c68822",
      "answer": false
    },
    {
      "questionId": "5246fb1f-d2ff-4208-986b-c75eef1726ef",
      "answer": true,
      "comment": "Ale před čím? Na to se otázka neptá. Určitě ne úkor  dálnic."
    },
    {
      "questionId": "dfa34db8-1fce-4e03-bc74-023c851635dc",
      "answer": true,
      "comment": "Vzhledem k nedostatku vody v některých regionech."
    },
    {
      "questionId": "a44b2eda-e3e9-46c0-84d3-b54384f69c4e",
      "answer": false,
      "comment": "Máme dobrý systém třídění."
    },
    {
      "questionId": "b52cb4c1-ec9d-40bc-9801-3d664a491d56",
      "answer": true,
      "comment": "Ovšem registrované partnerství nahradilo partnerství, kde jsou práva partnerů nově definivána. Takže ta otázka je trochu zavádějící. Ale jsem proto, aby stejno pohlavní  páry  měly práva heterosexuálních. Z devalvace “klasického” manželství a rozvratu se neobávám, stačí se podívat na tak katolické země jako Irsko a Španělsko. Žádná katastrofa se tam nekoná."
    },
    {
      "questionId": "5639fb63-b567-4961-8ce4-145eb286f3d3",
      "answer": false
    },
    {
      "questionId": "db9c7221-9a8d-44bb-af2b-47c8f6b03d56",
      "answer": true,
      "comment": "Pro vlastní potřebu, ale ne pro volný prodej."
    },
    {
      "questionId": "36847062-6427-40d0-80fb-f0f57934dc90",
      "answer": true,
      "comment": "Musím ale říci, že ani současné možné tresty soudci nevyužívají naplno. Ono to chce i edukaci soudců a žalobců, kteří řeší takové případy."
    },
    {
      "questionId": "931cf702-396e-4a2b-a0c7-db2a2d051f05",
      "answer": false,
      "comment": "Lepší je uvádět takové info na pravou míru"
    },
    {
      "questionId": "2deb4e7d-fc56-48b2-99c9-43ac0eb17809",
      "answer": false,
      "comment": "Dtto 17"
    },
    {
      "questionId": "7d1d35e0-12b5-46af-ac08-1c3c64862103",
      "answer": false,
      "comment": "Vzpomeňme na ČSR, která se podvolila Mnichovu, přišla o část území a Hitler pak přes všechna ujištění do zbytku republiky napochodoval. Nic to tedy nevyřešilo."
    },
    {
      "questionId": "9cf8aae5-681b-4fe7-b215-f0818f89b68e",
      "answer": true,
      "comment": "Když splní všechny podmínky, které musely splnit všechny členské země."
    },
    {
      "questionId": "07b8e1f9-79e1-4f17-af33-b9114e0bd75e",
      "answer": true,
      "comment": "Jinak se to bude moci opakovat."
    },
    {
      "questionId": "4bb73b72-2610-46e2-a891-f093858ae0ad",
      "answer": true,
      "comment": "Nejsem si však jistý, že takovéto jednostranné opatření evropských zemí, vůbec něco vyřeší, pokud vezmeme v úvahu  zejména Indii, Čínu, Afriku a latinskou Ameriku, kde to nikomu játra netrhá. Ale  vidím v tom současně i mnoho novych příležitostí."
    },
    {
      "questionId": "78d3f289-6d60-4af0-b2e9-06154ff4124c",
      "answer": true
    },
    {
      "questionId": "5f2bebd3-ed6b-44f6-971b-ceafeafd6cd4",
      "answer": true,
      "comment": "U nově vznikajících zcela určitě. Zvýší to prestiž a atraktivitu."
    },
    {
      "questionId": "c0a9c9c6-c36b-4c83-b02d-3f704f697d6c",
      "answer": false,
      "comment": "Pro on-line není správný čas s ohledem na skutečnost, že důvěra ve volby je velice citlivé téma a není na stole žádné opatření, jak zabránit útokům na elektronické volby."
    },
    {
      "questionId": "a94a2af4-3b3e-4a43-a936-4b393ddbcdb7",
      "answer": false
    },
    {
      "questionId": "b31ccd80-369f-4224-8e86-8aa44664b80b",
      "answer": true,
      "comment": "2016 byla inkluze zavedena do praxe. je tu 8 let a je možná čas na vyhodnocení a úpravu, to je určitě na místě."
    },
    {
      "questionId": "226b8e98-32b3-42f5-b4e4-6ab2b2b06c87",
      "answer": false,
      "comment": "Koment"
    },
    {
      "questionId": "7b3ac5c9-b2a2-45cc-928d-c876949a2b7f",
      "answer": false,
      "comment": "Zachování dostupné a kvalitní péče je i pro náš region velice  důležité. Nepovažuji za rozumné, soustředit je výlučně  do velké centrální nemocnice."
    },
    {
      "questionId": "e3c15681-0a1c-4e62-bc2f-2d89088856a9",
      "answer": null,
      "comment": "Pokud se nepletu, v ČR se už nesmí používat pro plodiny určené k přímému potravinářskému zpracování. U dalšího využití je to přípustné. Zvedám nás tím obočí, ale rad bych k rozhodnutí měl v ruce hodnověrné podklady."
    },
    {
      "questionId": "088029ea-c9fe-4abb-bdc7-4c1faa2c007f",
      "answer": true
    },
    {
      "questionId": "dc4b3ed9-80d5-4c0f-976b-9dd0f44b5df6",
      "answer": true,
      "comment": "Musíme ctít naše závazky vydávat na obranu 2% HDP."
    },
    {
      "questionId": "fc8daca8-7035-415c-9ab5-5cff0ec01e2c",
      "answer": false,
      "comment": "Bezpečnostní záruky v rozsahu NATO nic nenahradí."
    },
    {
      "questionId": "db7b8164-71d8-4f4b-8d78-4abebcc17847",
      "answer": true,
      "comment": "Pokud tedy dotace vůbec jsou vůbec rozumné. Obavám se však, že evropské zemědělství ke již natolik dotacemi deformované, že jejich odstřihnutí pouze v ČR, by bylo složité. Škodlivé  spíše než prospěšné."
    },
    {
      "questionId": "dbf45b5e-1e11-45e2-a037-18d9bf18353f",
      "answer": false,
      "comment": "Už teď je zdanění práce u nás jedno z nejvyšších."
    }
  ]
}