{
  "elections": [
    {
      "id": "presidential-2023",
      "key": "presidential-2023",
      "name": "Fontos választás 2023 - 1. forduló",
      "description": "Ez az ami az.",
      "instructions": {
        "header": "presidential - header",
        "step_1_1": "",
        "step_1_2": "",
        "step_1_link": "",
        "step_2_1": ""
      },
      "from": "2024-11-03T14:00:00",
      "to": "2025-01-24T14:00:00"
    }
  ],
  "calculators": [
    {
      "calculator_id": "2e0e6853-4305-4dec-abdc-a47d458b1b95",
      "election_id": "presidential-2023",
      "district_code": "national",
      "show_district_code": false,
      "name": "1. round",
      "description": "Kalkulačka vhodná pro všechny občany.",
      "on_hp_from": "2024-11-03T14:00:00",
      "on_hp_to": "2025-01-24T14:00:00"
    },
    {
      "calculator_id": "9327034e-dd2d-4be0-b50a-ea8cd590c82b",
      "election_id": "prezidentske-2023",
      "district_code": "national-2-round",
      "show_district_code": false,
      "name": "2. round",
      "description": "Kalkulačka vhodná pro všechny občany.",
      "on_hp_from": "2022-09-03T14:00:00",
      "on_hp_to": "2023-01-24T14:00:00"
    },
    {
      "calculator_id": "575a8e7b-b2a5-4257-9a61-c25db4242403",
      "election_id": "prezidentske-2023",
      "district_code": "pro-nadsence",
      "show_district_code": false,
      "name": "Pro nadšence",
      "description": "Kalkulačka vhodná pro všechny politické nadšence.",
      "on_hp_from": "2022-09-03T14:00:00",
      "on_hp_to": "2023-01-24T14:00:00"
    },
    {
      "calculator_id": "b82ed10e-72b3-4a3c-8019-e024fd8c1ea4",
      "election_id": "prezidentske-2023",
      "district_code": "pro-mlade",
      "show_district_code": false,
      "name": "Pro mladé",
      "description": "Kalkulačka vhodná pro všechny mladé občany.",
      "on_hp_from": "2022-09-03T14:00:00",
      "on_hp_to": "2023-01-24T14:00:00"
    }
  ]
}
